FreeProxyScraper/__init__.py
FreeProxyScraper/plugins/FreeProxy.py
FreeProxyScraper/plugins/__init__.py
FreeProxyScraper/plugins/examplePlugin.py
FreeProxyScraper/plugins/geonode.py
FreeProxyScraper/plugins/hidemy.py
FreeProxyScraper/plugins/spysone.py
FreeProxyScraper/plugins/sslproxies.py
FreeProxyScraper/utils/__init__.py
FreeProxyScraper/utils/decos.py
FreeProxyScraper/utils/plugins.py
FreeProxyScraper/utils/soup.py
FreeProxyScraper-0.1.17.dist-info/LICENSE
FreeProxyScraper-0.1.17.dist-info/METADATA
FreeProxyScraper-0.1.17.dist-info/WHEEL
FreeProxyScraper-0.1.17.dist-info/top_level.txt
FreeProxyScraper-0.1.17.dist-info/RECORD
