Metadata-Version: 2.1
Name: FreeProxyScraper
Version: 0.1.17
Summary: UNKNOWN
Home-page: https://github.com/Themis3000/FreeProxyScraper
Author: Themis3000
License: "MIT"
Platform: UNKNOWN
Classifier: Programming Language :: Python :: 3
Classifier: License :: OSI Approved :: MIT License
Classifier: Operating System :: OS Independent
Requires-Python: >=3.7
License-File: LICENSE
Requires-Dist: requests (>=2.26.0)
Requires-Dist: beautifulsoup4 (>=4.9.1)
Requires-Dist: fake-useragent (>=0.1.11)
